evaluix/CreateEvaluixConfig.py
evaluix/CustomWidgets.py
evaluix/DefaultProfile.yaml
evaluix/EvaluationFunctions.py
evaluix/EvaluixConfig.yaml
evaluix/FileLoader.py
evaluix/Macros.yaml
evaluix/__init__.py
evaluix/__main__.py
evaluix/__version__.py
evaluix/Icons/icon_hys_ArctanEval.png
evaluix/Icons/icon_hys_DoubleArctanEval.png
evaluix/Icons/icon_hys_LinEval.png
evaluix/Icons/icon_hys_center.png
evaluix/Icons/icon_hys_del_outliers.png
evaluix/Icons/icon_hys_noise_reduction.png
evaluix/Icons/icon_hys_norm_white.png
evaluix/Icons/icon_hys_num_derivative.png
evaluix/Icons/icon_hys_num_integral.png
evaluix/Icons/icon_hys_rmv_opening.png
evaluix/Icons/icon_hys_slope_corr.png
evaluix/Icons/icon_infosettings.png
evaluix/Icons/icon_infosettings_cropped.png
evaluix/Icons/icon_trashcan.png
evaluix/Icons/icon_trashcan_cropped.png
evaluix/Icons/old_icon_infosettings.png
evaluix/Icons/old_icon_infosettings_cropped.png
evaluix2-0.9.1.dist-info/METADATA
evaluix2-0.9.1.dist-info/WHEEL
evaluix2-0.9.1.dist-info/entry_points.txt
evaluix2-0.9.1.dist-info/top_level.txt
evaluix2-0.9.1.dist-info/RECORD
