Metadata-Version: 2.1
Name: evaluix2
Version: 0.9.1
Summary: Data Evaluation Software of Arbeitsgruppe Ehresmann (Magnetism)
Home-page: https://github.com/exp4-age/evaluix
Author: Arne Jan Vereijken
Author-email: arne.vereijken@physik.uni-kassel.de
License: MIT
Classifier: Programming Language :: Python :: 3
Classifier: License :: OSI Approved :: MIT License
Classifier: Operating System :: OS Independent
Requires-Python: >=3.9
Requires-Dist: exp4-agepy >=0.2
Requires-Dist: numpy >=1.24.2
Requires-Dist: matplotlib
Requires-Dist: pandas
Requires-Dist: scipy
Requires-Dist: pyyaml
Requires-Dist: h5py
Requires-Dist: scikit-learn
Requires-Dist: scikit-image
Requires-Dist: ipython-genutils
Requires-Dist: ipykernel >=6.0.3
Requires-Dist: NSFopen >=2.0.0
Requires-Dist: pyqt6 >=6.4.2
Requires-Dist: lmfit
